thevk/__init__.py
thevk/flipkartscraper.py
flipkart_scraper-0.1.dist-info/METADATA
flipkart_scraper-0.1.dist-info/WHEEL
flipkart_scraper-0.1.dist-info/top_level.txt
flipkart_scraper-0.1.dist-info/RECORD
