Metadata-Version: 2.1
Name: flipkart-scraper
Version: 0.1
Summary: A Flipkart scraper for extracting product information
Home-page: https://github.com/mdvenukumar/flipkart-scraper
Author: Mutyala Durga Venu Kumar
Author-email: thevk22@gmail.com
Project-URL: Source, https://github.com/mdvenukumar/flipkart-scraper
Project-URL: Bug Reports, https://github.com/mdvenukumar/flipkart-scraper/issues
Keywords: flipkart scraper web scraping
Classifier: Development Status :: 3 - Alpha
Classifier: Intended Audience :: Developers
Classifier: Topic :: Software Development :: Libraries :: Python Modules
Classifier: License :: OSI Approved :: MIT License
Classifier: Programming Language :: Python :: 3
Classifier: Programming Language :: Python :: 3.6
Classifier: Programming Language :: Python :: 3.7
Classifier: Programming Language :: Python :: 3.8
Classifier: Programming Language :: Python :: 3.9
Requires-Dist: requests
Requires-Dist: beautifulsoup4
